<Properties StartupConfiguration="{19011A29-6E4D-4B61-BB38-C971835948F2}|Default">
  <MonoDevelop.Ide.DebuggingService.Breakpoints>
    <BreakpointStore />
  </MonoDevelop.Ide.DebuggingService.Breakpoints>
  <MonoDevelop.Ide.DebuggingService.PinnedWatches />
  <MonoDevelop.Ide.Workbench ActiveDocument="../../BBook/BulkyBookWeb/appsettings.json">
    <Files>
      <File FileName="appsettings.json" Line="14" Column="1" />
      <File FileName="Program.cs" Line="31" Column="1" />
      <File FileName="../../BBook/BulkyBookWeb/appsettings.json" Line="16" Column="1" />
      <File FileName="../../BBook/BulkyBookWeb/Program.cs" Line="19" Column="2" />
    </Files>
    <Pads>
      <Pad Id="ProjectPad">
        <State name="__root__">
          <Node name="FinancialApp" expanded="True">
            <Node name="BulkyBookWeb" selected="True" />
            <Node name="FinancialApp" expanded="True">
              <Node name="Properties" expanded="True" />
            </Node>
          </Node>
        </State>
      </Pad>
    </Pads>
  </MonoDevelop.Ide.Workbench>
  <MonoDevelop.Ide.Workspace ActiveConfiguration="Debug" />
  <MonoDevelop.Ide.ItemProperties.FinancialApp PreferredExecutionTarget="/Applications/Google Chrome.app" />
  <MultiItemStartupConfigurations />
</Properties>